pybindx/__init__.py
pybindx/generators.py
pybindx/input/__init__.py
pybindx/input/base_info.py
pybindx/input/class_info.py
pybindx/input/cpp_type_info.py
pybindx/input/enum_info.py
pybindx/input/free_function_info.py
pybindx/input/info_helper.py
pybindx/input/method_info.py
pybindx/input/module_info.py
pybindx/input/package_info.py
pybindx/input/variable_info.py
pybindx/parsers/__init__.py
pybindx/parsers/package_info.py
pybindx/parsers/source_parser.py
pybindx/templates/__init__.py
pybindx/templates/custom.py
pybindx/templates/pybind11_default.py
pybindx/writers/__init__.py
pybindx/writers/base_writer.py
pybindx/writers/class_arg_writer.py
pybindx/writers/class_writer.py
pybindx/writers/classes_writer.py
pybindx/writers/constructor_writer.py
pybindx/writers/enum_writer.py
pybindx/writers/free_function_writer.py
pybindx/writers/header_collection_writer.py
pybindx/writers/method_writer.py
pybindx/writers/module_writer.py
pybindx-1.1.22.dist-info/LICENSE
pybindx-1.1.22.dist-info/METADATA
pybindx-1.1.22.dist-info/WHEEL
pybindx-1.1.22.dist-info/top_level.txt
pybindx-1.1.22.dist-info/RECORD
