Metadata-Version: 2.1
Name: pybindx
Version: 1.1.22
Summary: a simple auto generate for pybind11, could worked with only head file
Home-page: UNKNOWN
Author: Alex Xiong
License: UNKNOWN
Keywords: autogenerate,pybind11
Platform: UNKNOWN
License-File: LICENSE
Requires-Dist: pygccxml
Requires-Dist: pyyaml
